controlcenter/__init__.py
controlcenter/app_settings.py
controlcenter/base.py
controlcenter/dashboards.py
controlcenter/utils.py
controlcenter/views.py
controlcenter/images/chart-no-data.png
controlcenter/images/widget-out.png
controlcenter/images/widget-stripes.png
controlcenter/images/widget-tab.png
controlcenter/static/controlcenter/css/all.css
controlcenter/static/controlcenter/css/chartist-default-colors.css
controlcenter/static/controlcenter/css/chartist-material-colors.css
controlcenter/static/controlcenter/css/chartist.css
controlcenter/static/controlcenter/css/chartist.css.map
controlcenter/static/controlcenter/js/masonry.pkgd.min.js
controlcenter/static/controlcenter/js/scripts.js
controlcenter/static/controlcenter/js/sortable.min.js
controlcenter/static/controlcenter/js/chartist/chartist-plugin-pointlabels.min.js
controlcenter/static/controlcenter/js/chartist/chartist-plugin-pointlabels.min.js.map
controlcenter/static/controlcenter/js/chartist/chartist.min.js
controlcenter/static/controlcenter/js/chartist/chartist.min.js.map
controlcenter/stylus/all.styl
controlcenter/stylus/chartist-default-colors.styl
controlcenter/stylus/chartist-material-colors.styl
controlcenter/stylus/mixins.styl
controlcenter/stylus/variables.styl
controlcenter/templates/controlcenter/dashboard.html
controlcenter/templates/controlcenter/snippets/generic_item.html
controlcenter/templates/controlcenter/widgets/chart.html
controlcenter/templates/controlcenter/widgets/itemlist.html
controlcenter/templates/controlcenter/widgets/contrib/key_value_list.html
controlcenter/templates/controlcenter/widgets/contrib/value_list.html
controlcenter/templatetags/__init__.py
controlcenter/templatetags/controlcenter_tags.py
controlcenter/widgets/__init__.py
controlcenter/widgets/charts.py
controlcenter/widgets/core.py
controlcenter/widgets/contrib/__init__.py
controlcenter/widgets/contrib/simple.py
django_controlcenter-0.3.3.dist-info/licenses/LICENSE
tests/__init__.py
tests/test_app_settings.py
tests/test_base.py
tests/test_dashboards.py
django_controlcenter-0.3.3.dist-info/METADATA
django_controlcenter-0.3.3.dist-info/WHEEL
django_controlcenter-0.3.3.dist-info/top_level.txt
django_controlcenter-0.3.3.dist-info/RECORD
